pydash/__init__.py
tests/__init__.py
tests/test_string.py
pydash_arnu515-1.0.1.dist-info/LICENSE
pydash_arnu515-1.0.1.dist-info/METADATA
pydash_arnu515-1.0.1.dist-info/WHEEL
pydash_arnu515-1.0.1.dist-info/top_level.txt
pydash_arnu515-1.0.1.dist-info/RECORD
